skaff_pirate_speak_configurable/__init__.py
skaff_pirate_speak_configurable/chain.py
skaff_pirate_speak_configurable-0.0.1.dist-info/LICENSE
skaff_pirate_speak_configurable-0.0.1.dist-info/METADATA
skaff_pirate_speak_configurable-0.0.1.dist-info/WHEEL
skaff_pirate_speak_configurable-0.0.1.dist-info/RECORD
