Metadata-Version: 2.1
Name: skaff-pirate-speak-configurable
Version: 0.0.1
Summary: Use Configurable Alternatives to allow clients to choose their Runnables
Requires-Python: >=3.8.1,<4.0
Classifier: Programming Language :: Python :: 3
Classifier: Programming Language :: Python :: 3.9
Classifier: Programming Language :: Python :: 3.10
Classifier: Programming Language :: Python :: 3.11
Requires-Dist: anthropic (>=0.6.0,<0.7.0)
Requires-Dist: cohere (>=4.34,<5.0)
Requires-Dist: langchain (>=0.1,<0.2)
Requires-Dist: langchain-mistralai (>=0.1.2,<0.2.0)
Requires-Dist: openai (<2)
